glasswall_visual_comparison_tool_cli/__init__.py
glasswall_visual_comparison_tool_cli/__main__.py
glasswall_visual_layer_comparison_tool_cli-1.0.11.dist-info/LICENSE
glasswall_visual_layer_comparison_tool_cli-1.0.11.dist-info/METADATA
glasswall_visual_layer_comparison_tool_cli-1.0.11.dist-info/WHEEL
glasswall_visual_layer_comparison_tool_cli-1.0.11.dist-info/entry_points.txt
glasswall_visual_layer_comparison_tool_cli-1.0.11.dist-info/top_level.txt
glasswall_visual_layer_comparison_tool_cli-1.0.11.dist-info/RECORD
