Metadata-Version: 2.1
Name: glasswall-visual-layer-comparison-tool-cli
Version: 1.0.11
Summary: CLI Tool that makes requests to the glasswall-visual-layer-comparison API
Home-page: https://github.com/filetrust/glasswall-visual-layer-comparison-tool-cli
Author: ahewitt
Author-email: ahewitt@glasswallsolutions.com
License: UNKNOWN
Platform: UNKNOWN
Classifier: Programming Language :: Python :: 3.8
Requires-Python: >=3.6
Requires-Dist: Click (>=7.0)
Requires-Dist: requests (>=2.23.0)
